kanapy/__init__.py
kanapy/texture.py
kanapy/core/__init__.py
kanapy/core/api.py
kanapy/core/cli.py
kanapy/core/collisions.py
kanapy/core/entities.py
kanapy/core/grains.py
kanapy/core/gui.py
kanapy/core/initializations.py
kanapy/core/input_output.py
kanapy/core/packing.py
kanapy/core/plotting.py
kanapy/core/rve_stats.py
kanapy/core/smoothingGB.py
kanapy/core/voxelization.py
kanapy-6.5.3.post1.dist-info/licenses/LICENSE
kanapy-6.5.3.post1.dist-info/METADATA
kanapy-6.5.3.post1.dist-info/WHEEL
kanapy-6.5.3.post1.dist-info/entry_points.txt
kanapy-6.5.3.post1.dist-info/top_level.txt
kanapy-6.5.3.post1.dist-info/RECORD
