Metadata-Version: 2.4
Name: kanapy
Version: 6.5.3.post1
Summary: Kanapy: Python package for microstructure analyse and generation of microstructure models
Author: Mahesh R.G. Prasad, Abhishek Biswas, Golsa Tolooei Eshlaghi, Ronak Shoghi, Napat Vajragupta, Yousef Rezek, Hrushikesh Uday Bhimavarapu
Author-email: Alexander Hartmaier <alexander.hartmaier@rub.de>
License-Expression: AGPL-3.0-or-later
Project-URL: Homepage, https://github.com/ICAMS/Kanapy
Classifier: Development Status :: 4 - Beta
Classifier: Intended Audience :: Science/Research
Classifier: Natural Language :: English
Classifier: Programming Language :: Python :: 3.9
Classifier: Programming Language :: Python :: 3.10
Classifier: Programming Language :: Python :: 3.11
Classifier: Programming Language :: Python :: 3.12
Classifier: Topic :: Scientific/Engineering :: Physics
Requires-Python: <3.13,>=3.9
License-File: LICENSE
Requires-Dist: numpy<=2.2.6
Requires-Dist: matplotlib
Requires-Dist: scipy
Requires-Dist: seaborn
Requires-Dist: click
Requires-Dist: tqdm
Requires-Dist: jsonschema
Requires-Dist: requests
Requires-Dist: orix>=0.13
Requires-Dist: networkx
Requires-Dist: scikit-image
Provides-Extra: mtex
Requires-Dist: kanapy-mtex>=6.5.0; extra == "mtex"
Provides-Extra: dev
Requires-Dist: pytest; extra == "dev"
Requires-Dist: pytest-mock; extra == "dev"
Requires-Dist: pytest-cov; extra == "dev"
Requires-Dist: black; extra == "dev"
Requires-Dist: build; extra == "dev"
Requires-Dist: twine; extra == "dev"
Dynamic: license-file
